[
    [
        {
            "team1Name": "Davenport Cliff Divers",
            "team1Abbr": "DCD",
            "team2Name": "Carmel Yacht Club",
            "team2Abbr": "CYC",
            "patternName": "random",
            "season": 13,
            "day": 0,
            "id": "dd90790f-cbb3-4271-a7d1-5ffc624fa4ed",
            "isPostseason": false,
            "league": "Monterey Bay League",
            "team1Color": "#f2c57c",
            "team2Color": "#e7d7c1"
        },
        {
            "team1Name": "Boulder Creek Cardsharps",
            "team1Abbr": "BCC",
            "team2Name": "Moss Landing Daredevils",
            "team2Abbr": "DD",
            "patternName": "dinnerplate",
            "season": 13,
            "day": 0,
            "id": "1b2be0e7-5167-4332-8a49-69e02d4511fc",
            "isPostseason": false,
            "league": "Monterey Bay League",
            "team1Color": "#00cc44",
            "team2Color": "#9963ab"
        },
        {
            "team1Name": "Pacific Grove Monarchists",
            "team1Abbr": "PGM",
            "team2Name": "Monterey Meteorologists",
            "team2Abbr": "MM",
            "patternName": "fishsoup",
            "season": 13,
            "day": 0,
            "id": "90f83e16-cf6f-4719-93e6-752d73f9ce58",
            "isPostseason": false,
            "league": "Monterey Bay League",
            "team1Color": "#e86215",
            "team2Color": "#ff66cc"
        },
        {
            "team1Name": "Aptos Investigators",
            "team1Abbr": "AI",
            "team2Name": "Freedom Fries",
            "team2Abbr": "FFR",
            "patternName": "denaturation",
            "season": 13,
            "day": 0,
            "id": "ca9b6a0f-14ce-4155-91a3-3c930b101bb4",
            "isPostseason": false,
            "league": "Monterey Bay League",
            "team1Color": "#3e92cc",
            "team2Color": "#a0e7e5"
        },
        {
            "team1Name": "Santa Cruz Bananas",
            "team1Abbr": "SCB",
            "team2Name": "Sand City Sidewinders",
            "team2Abbr": "SCS",
            "patternName": "fishsoup",
            "season": 13,
            "day": 0,
            "id": "1cafe2c5-ea8f-4da1-9695-036e50dc7428",
            "isPostseason": false,
            "league": "Monterey Bay League",
            "team1Color": "#fefe67",
            "team2Color": "#bb0000"
        },
        {
            "team1Name": "San Jose Avionics",
            "team1Abbr": "SJA",
            "team2Name": "Sutro Tower",
            "team2Abbr": "ST",
            "patternName": "fishsoup",
            "season": 13,
            "day": 0,
            "id": "bd0803f2-4fb0-4241-b2d6-3587cf336b49",
            "isPostseason": false,
            "league": "San Francisco Bay League",
            "team1Color": "#53917e",
            "team2Color": "#ff1717"
        },
        {
            "team1Name": "Vallejo Barnstormers",
            "team1Abbr": "VB",
            "team2Name": "Hayward Pipelines",
            "team2Abbr": "HP",
            "patternName": "kitchensink",
            "season": 13,
            "day": 0,
            "id": "440ed9fa-a565-46f8-8925-c3f11a2cceaf",
            "isPostseason": false,
            "league": "San Francisco Bay League",
            "team1Color": "#697a21",
            "team2Color": "#b0b0b0"
        },
        {
            "team1Name": "Richmond Slicks",
            "team1Abbr": "RS",
            "team2Name": "Oakland Bees",
            "team2Abbr": "OB",
            "patternName": "chicago",
            "season": 13,
            "day": 0,
            "id": "09ab1c8f-1e9e-4443-b4d8-1740b7fa466e",
            "isPostseason": false,
            "league": "San Francisco Bay League",
            "team1Color": "#e7a0e8",
            "team2Color": "#ffb627"
        },
        {
            "team1Name": "Sausalito Bouncy Castles",
            "team1Abbr": "SBC",
            "team2Name": "Berkeley Brutalists",
            "team2Abbr": "BBR",
            "patternName": "evaporation",
            "season": 13,
            "day": 0,
            "id": "dad79556-7e0d-4148-8edf-7bc1ce4a4ff7",
            "isPostseason": false,
            "league": "San Francisco Bay League",
            "team1Color": "#0dab76",
            "team2Color": "#d41199"
        },
        {
            "team1Name": "San Gregorio Sand Crabs",
            "team1Abbr": "SGSC",
            "team2Name": "Mountain View Miners",
            "team2Abbr": "MVM",
            "patternName": "fishsoup",
            "season": 13,
            "day": 0,
            "id": "fd305267-7fcb-478c-99e0-08b1930a14a7",
            "isPostseason": false,
            "league": "San Francisco Bay League",
            "team1Color": "#ef6f6c",
            "team2Color": "#f08700"
        }
    ],
    [
        {
            "team1Name": "Moss Landing Daredevils",
            "team1Abbr": "DD",
            "team2Name": "Freedom Fries",
            "team2Abbr": "FFR",
            "patternName": "chicago",
            "season": 13,
            "day": 1,
            "id": "1b916655-eee6-48be-b8ba-a80d1ef2e14d",
            "isPostseason": false,
            "league": "Monterey Bay League",
            "team1Color": "#9963ab",
            "team2Color": "#a0e7e5"
        },
        {
            "team1Name": "Sand City Sidewinders",
            "team1Abbr": "SCS",
            "team2Name": "Davenport Cliff Divers",
            "team2Abbr": "DCD",
            "patternName": "squarestar",
            "season": 13,
            "day": 1,
            "id": "4d5f981f-9439-4d7d-8d7e-e5857d03a0b0",
            "isPostseason": false,
            "league": "Monterey Bay League",
            "team1Color": "#bb0000",
            "team2Color": "#f2c57c"
        },
        {
            "team1Name": "Monterey Meteorologists",
            "team1Abbr": "MM",
            "team2Name": "Santa Cruz Bananas",
            "team2Abbr": "SCB",
            "patternName": "denaturation",
            "season": 13,
            "day": 1,
            "id": "061e8f78-a356-4d9f-a23d-0e599ec750e5",
            "isPostseason": false,
            "league": "Monterey Bay League",
            "team1Color": "#ff66cc",
            "team2Color": "#fefe67"
        },
        {
            "team1Name": "Pacific Grove Monarchists",
            "team1Abbr": "PGM",
            "team2Name": "Carmel Yacht Club",
            "team2Abbr": "CYC",
            "patternName": "newyork",
            "season": 13,
            "day": 1,
            "id": "f43d6d9e-6a2a-4671-9adc-94d6bdc90662",
            "isPostseason": false,
            "league": "Monterey Bay League",
            "team1Color": "#e86215",
            "team2Color": "#e7d7c1"
        },
        {
            "team1Name": "Aptos Investigators",
            "team1Abbr": "AI",
            "team2Name": "Boulder Creek Cardsharps",
            "team2Abbr": "BCC",
            "patternName": "fishsoup",
            "season": 13,
            "day": 1,
            "id": "8bbb7a36-6f60-4e41-9288-f8618eb9319a",
            "isPostseason": false,
            "league": "Monterey Bay League",
            "team1Color": "#3e92cc",
            "team2Color": "#00cc44"
        },
        {
            "team1Name": "Sutro Tower",
            "team1Abbr": "ST",
            "team2Name": "San Jose Avionics",
            "team2Abbr": "SJA",
            "patternName": "kitchensink",
            "season": 13,
            "day": 1,
            "id": "d47c5b95-f630-49ec-88f9-7055e7b8d975",
            "isPostseason": false,
            "league": "San Francisco Bay League",
            "team1Color": "#ff1717",
            "team2Color": "#53917e"
        },
        {
            "team1Name": "Berkeley Brutalists",
            "team1Abbr": "BBR",
            "team2Name": "Hayward Pipelines",
            "team2Abbr": "HP",
            "patternName": "chicago",
            "season": 13,
            "day": 1,
            "id": "be21bbb0-cbe3-46c2-862c-0ee6ef288d04",
            "isPostseason": false,
            "league": "San Francisco Bay League",
            "team1Color": "#d41199",
            "team2Color": "#b0b0b0"
        },
        {
            "team1Name": "Sausalito Bouncy Castles",
            "team1Abbr": "SBC",
            "team2Name": "Richmond Slicks",
            "team2Abbr": "RS",
            "patternName": "chicago",
            "season": 13,
            "day": 1,
            "id": "c06da3eb-7a35-4e9b-91cd-757b5824ec1d",
            "isPostseason": false,
            "league": "San Francisco Bay League",
            "team1Color": "#0dab76",
            "team2Color": "#e7a0e8"
        },
        {
            "team1Name": "San Gregorio Sand Crabs",
            "team1Abbr": "SGSC",
            "team2Name": "Oakland Bees",
            "team2Abbr": "OB",
            "patternName": "denaturation",
            "season": 13,
            "day": 1,
            "id": "4cb4e6c6-3633-4e2d-b30a-73fcd3fe3a1b",
            "isPostseason": false,
            "league": "San Francisco Bay League",
            "team1Color": "#ef6f6c",
            "team2Color": "#ffb627"
        },
        {
            "team1Name": "Vallejo Barnstormers",
            "team1Abbr": "VB",
            "team2Name": "Mountain View Miners",
            "team2Abbr": "MVM",
            "patternName": "stlouis",
            "season": 13,
            "day": 1,
            "id": "60132892-c930-4bf1-8ae4-073b1f625be8",
            "isPostseason": false,
            "league": "San Francisco Bay League",
            "team1Color": "#697a21",
            "team2Color": "#f08700"
        }
    ],
    [
        {
            "team1Name": "Boulder Creek Cardsharps",
            "team1Abbr": "BCC",
            "team2Name": "Santa Cruz Bananas",
            "team2Abbr": "SCB",
            "patternName": "denaturation",
            "season": 13,
            "day": 2,
            "id": "bc0ce111-1088-48c5-8ec3-fa34c9b0d428",
            "isPostseason": false,
            "league": "Monterey Bay League",
            "team1Color": "#00cc44",
            "team2Color": "#fefe67"
        },
        {
            "team1Name": "Sand City Sidewinders",
            "team1Abbr": "SCS",
            "team2Name": "Aptos Investigators",
            "team2Abbr": "AI",
            "patternName": "rustytank",
            "season": 13,
            "day": 2,
            "id": "991a32b8-2d7b-4609-953d-0791ef9fad45",
            "isPostseason": false,
            "league": "Monterey Bay League",
            "team1Color": "#bb0000",
            "team2Color": "#3e92cc"
        },
        {
            "team1Name": "Freedom Fries",
            "team1Abbr": "FFR",
            "team2Name": "Pacific Grove Monarchists",
            "team2Abbr": "PGM",
            "patternName": "kitchensink",
            "season": 13,
            "day": 2,
            "id": "727b3e44-c461-417a-b407-644860c6f6a4",
            "isPostseason": false,
            "league": "Monterey Bay League",
            "team1Color": "#a0e7e5",
            "team2Color": "#e86215"
        },
        {
            "team1Name": "Moss Landing Daredevils",
            "team1Abbr": "DD",
            "team2Name": "Carmel Yacht Club",
            "team2Abbr": "CYC",
            "patternName": "kitchensink",
            "season": 13,
            "day": 2,
            "id": "1fbeb3f5-8401-4175-8dc3-3aeab122bf47",
            "isPostseason": false,
            "league": "Monterey Bay League",
            "team1Color": "#9963ab",
            "team2Color": "#e7d7c1"
        },
        {
            "team1Name": "Monterey Meteorologists",
            "team1Abbr": "MM",
            "team2Name": "Davenport Cliff Divers",
            "team2Abbr": "DCD",
            "patternName": "flyingv1",
            "season": 13,
            "day": 2,
            "id": "bccd10db-e7b7-4a8e-a5fa-b91a2519438f",
            "isPostseason": false,
            "league": "Monterey Bay League",
            "team1Color": "#ff66cc",
            "team2Color": "#f2c57c"
        },
        {
            "team1Name": "San Jose Avionics",
            "team1Abbr": "SJA",
            "team2Name": "Vallejo Barnstormers",
            "team2Abbr": "VB",
            "patternName": "evaporation",
            "season": 13,
            "day": 2,
            "id": "34e454cf-c3c3-42c7-a640-1488db4a8962",
            "isPostseason": false,
            "league": "San Francisco Bay League",
            "team1Color": "#53917e",
            "team2Color": "#697a21"
        },
        {
            "team1Name": "Sausalito Bouncy Castles",
            "team1Abbr": "SBC",
            "team2Name": "Oakland Bees",
            "team2Abbr": "OB",
            "patternName": "flyingv2",
            "season": 13,
            "day": 2,
            "id": "db3161c2-7151-47f6-bbcd-d83a24cc2979",
            "isPostseason": false,
            "league": "San Francisco Bay League",
            "team1Color": "#0dab76",
            "team2Color": "#ffb627"
        },
        {
            "team1Name": "Berkeley Brutalists",
            "team1Abbr": "BBR",
            "team2Name": "Richmond Slicks",
            "team2Abbr": "RS",
            "patternName": "precipitation",
            "season": 13,
            "day": 2,
            "id": "12e4fd42-73d7-4763-8d1d-9331302ef930",
            "isPostseason": false,
            "league": "San Francisco Bay League",
            "team1Color": "#d41199",
            "team2Color": "#e7a0e8"
        },
        {
            "team1Name": "Mountain View Miners",
            "team1Abbr": "MVM",
            "team2Name": "Hayward Pipelines",
            "team2Abbr": "HP",
            "patternName": "fishsoup",
            "season": 13,
            "day": 2,
            "id": "5147b8a8-32df-4330-9018-1e7301a17d49",
            "isPostseason": false,
            "league": "San Francisco Bay League",
            "team1Color": "#f08700",
            "team2Color": "#b0b0b0"
        },
        {
            "team1Name": "San Gregorio Sand Crabs",
            "team1Abbr": "SGSC",
            "team2Name": "Sutro Tower",
            "team2Abbr": "ST",
            "patternName": "dessertplate",
            "season": 13,
            "day": 2,
            "id": "119984d3-ed54-4690-8479-39fe3899d490",
            "isPostseason": false,
            "league": "San Francisco Bay League",
            "team1Color": "#ef6f6c",
            "team2Color": "#ff1717"
        }
    ],
    [
        {
            "team1Name": "Freedom Fries",
            "team1Abbr": "FFR",
            "team2Name": "Aptos Investigators",
            "team2Abbr": "AI",
            "patternName": "newyork",
            "season": 13,
            "day": 3,
            "id": "8f69d1f5-993c-40af-b952-00a30d804b63",
            "isPostseason": false,
            "league": "Monterey Bay League",
            "team1Color": "#a0e7e5",
            "team2Color": "#3e92cc"
        },
        {
            "team1Name": "Boulder Creek Cardsharps",
            "team1Abbr": "BCC",
            "team2Name": "Pacific Grove Monarchists",
            "team2Abbr": "PGM",
            "patternName": "precipitation",
            "season": 13,
            "day": 3,
            "id": "77257a53-8c5f-4a26-8018-2e35d6d80a4c",
            "isPostseason": false,
            "league": "Monterey Bay League",
            "team1Color": "#00cc44",
            "team2Color": "#e86215"
        },
        {
            "team1Name": "Sand City Sidewinders",
            "team1Abbr": "SCS",
            "team2Name": "Santa Cruz Bananas",
            "team2Abbr": "SCB",
            "patternName": "dessertplate",
            "season": 13,
            "day": 3,
            "id": "5b4a68ee-dd89-4704-a421-b50c0e3070dd",
            "isPostseason": false,
            "league": "Monterey Bay League",
            "team1Color": "#bb0000",
            "team2Color": "#fefe67"
        },
        {
            "team1Name": "Davenport Cliff Divers",
            "team1Abbr": "DCD",
            "team2Name": "Carmel Yacht Club",
            "team2Abbr": "CYC",
            "patternName": "flyingv1",
            "season": 13,
            "day": 3,
            "id": "1cbf8cda-d9ec-4c01-ac50-ec328d2fe6bb",
            "isPostseason": false,
            "league": "Monterey Bay League",
            "team1Color": "#f2c57c",
            "team2Color": "#e7d7c1"
        },
        {
            "team1Name": "Monterey Meteorologists",
            "team1Abbr": "MM",
            "team2Name": "Moss Landing Daredevils",
            "team2Abbr": "DD",
            "patternName": "denaturation",
            "season": 13,
            "day": 3,
            "id": "814f00ee-d7ac-444b-a612-85262f3bd5c4",
            "isPostseason": false,
            "league": "Monterey Bay League",
            "team1Color": "#ff66cc",
            "team2Color": "#9963ab"
        },
        {
            "team1Name": "Hayward Pipelines",
            "team1Abbr": "HP",
            "team2Name": "Oakland Bees",
            "team2Abbr": "OB",
            "patternName": "combs",
            "season": 13,
            "day": 3,
            "id": "0163c1c4-03a3-496f-a47b-afee300868f4",
            "isPostseason": false,
            "league": "San Francisco Bay League",
            "team1Color": "#b0b0b0",
            "team2Color": "#ffb627"
        },
        {
            "team1Name": "Berkeley Brutalists",
            "team1Abbr": "BBR",
            "team2Name": "San Gregorio Sand Crabs",
            "team2Abbr": "SGSC",
            "patternName": "chicago",
            "season": 13,
            "day": 3,
            "id": "03185047-69d0-4a9c-b2f2-889fa96d3b32",
            "isPostseason": false,
            "league": "San Francisco Bay League",
            "team1Color": "#d41199",
            "team2Color": "#ef6f6c"
        },
        {
            "team1Name": "San Jose Avionics",
            "team1Abbr": "SJA",
            "team2Name": "Sausalito Bouncy Castles",
            "team2Abbr": "SBC",
            "patternName": "random",
            "season": 13,
            "day": 3,
            "id": "f8ca7b69-7433-462a-bab7-59adc145b263",
            "isPostseason": false,
            "league": "San Francisco Bay League",
            "team1Color": "#53917e",
            "team2Color": "#0dab76"
        },
        {
            "team1Name": "Mountain View Miners",
            "team1Abbr": "MVM",
            "team2Name": "Vallejo Barnstormers",
            "team2Abbr": "VB",
            "patternName": "newyork",
            "season": 13,
            "day": 3,
            "id": "4441b44a-cacb-4a20-9e5b-8216e1d6a25f",
            "isPostseason": false,
            "league": "San Francisco Bay League",
            "team1Color": "#f08700",
            "team2Color": "#697a21"
        },
        {
            "team1Name": "Sutro Tower",
            "team1Abbr": "ST",
            "team2Name": "Richmond Slicks",
            "team2Abbr": "RS",
            "patternName": "fishsoup",
            "season": 13,
            "day": 3,
            "id": "d19a3ade-e003-4769-ab4e-53fd5d18dce0",
            "isPostseason": false,
            "league": "San Francisco Bay League",
            "team1Color": "#ff1717",
            "team2Color": "#e7a0e8"
        }
    ],
    [
        {
            "team1Name": "Sand City Sidewinders",
            "team1Abbr": "SCS",
            "team2Name": "Freedom Fries",
            "team2Abbr": "FFR",
            "patternName": "combs",
            "season": 13,
            "day": 4,
            "id": "c8f687b7-6875-4f7e-8461-d14713bb39fb",
            "isPostseason": false,
            "league": "Monterey Bay League",
            "team1Color": "#bb0000",
            "team2Color": "#a0e7e5"
        },
        {
            "team1Name": "Moss Landing Daredevils",
            "team1Abbr": "DD",
            "team2Name": "Santa Cruz Bananas",
            "team2Abbr": "SCB",
            "patternName": "precipitation",
            "season": 13,
            "day": 4,
            "id": "3e093eff-4079-485e-8639-2f81bedfe196",
            "isPostseason": false,
            "league": "Monterey Bay League",
            "team1Color": "#9963ab",
            "team2Color": "#fefe67"
        },
        {
            "team1Name": "Boulder Creek Cardsharps",
            "team1Abbr": "BCC",
            "team2Name": "Carmel Yacht Club",
            "team2Abbr": "CYC",
            "patternName": "stlouis",
            "season": 13,
            "day": 4,
            "id": "bd3dd0ac-d303-48c4-907b-e57128fd2608",
            "isPostseason": false,
            "league": "Monterey Bay League",
            "team1Color": "#00cc44",
            "team2Color": "#e7d7c1"
        },
        {
            "team1Name": "Pacific Grove Monarchists",
            "team1Abbr": "PGM",
            "team2Name": "Aptos Investigators",
            "team2Abbr": "AI",
            "patternName": "precipitation",
            "season": 13,
            "day": 4,
            "id": "34581f15-f33a-46b7-82df-1716bba6689f",
            "isPostseason": false,
            "league": "Monterey Bay League",
            "team1Color": "#e86215",
            "team2Color": "#3e92cc"
        },
        {
            "team1Name": "Davenport Cliff Divers",
            "team1Abbr": "DCD",
            "team2Name": "Monterey Meteorologists",
            "team2Abbr": "MM",
            "patternName": "dinnerplate",
            "season": 13,
            "day": 4,
            "id": "315b2790-1d05-4195-b7ca-b6ac8e762425",
            "isPostseason": false,
            "league": "Monterey Bay League",
            "team1Color": "#f2c57c",
            "team2Color": "#ff66cc"
        },
        {
            "team1Name": "San Gregorio Sand Crabs",
            "team1Abbr": "SGSC",
            "team2Name": "Vallejo Barnstormers",
            "team2Abbr": "VB",
            "patternName": "ricepudding",
            "season": 13,
            "day": 4,
            "id": "d1cd9a3b-23ea-4d18-b347-aa3e4108ca6b",
            "isPostseason": false,
            "league": "San Francisco Bay League",
            "team1Color": "#ef6f6c",
            "team2Color": "#697a21"
        },
        {
            "team1Name": "Berkeley Brutalists",
            "team1Abbr": "BBR",
            "team2Name": "Mountain View Miners",
            "team2Abbr": "MVM",
            "patternName": "denaturation",
            "season": 13,
            "day": 4,
            "id": "10c2eea4-3ffe-4552-9ffc-ca8652179f65",
            "isPostseason": false,
            "league": "San Francisco Bay League",
            "team1Color": "#d41199",
            "team2Color": "#f08700"
        },
        {
            "team1Name": "Hayward Pipelines",
            "team1Abbr": "HP",
            "team2Name": "Sausalito Bouncy Castles",
            "team2Abbr": "SBC",
            "patternName": "kitchensink",
            "season": 13,
            "day": 4,
            "id": "347bee4f-5f9a-45b4-a19a-fb69234e7d31",
            "isPostseason": false,
            "league": "San Francisco Bay League",
            "team1Color": "#b0b0b0",
            "team2Color": "#0dab76"
        },
        {
            "team1Name": "San Jose Avionics",
            "team1Abbr": "SJA",
            "team2Name": "Oakland Bees",
            "team2Abbr": "OB",
            "patternName": "precipitation",
            "season": 13,
            "day": 4,
            "id": "62df58c0-ba1e-432e-9684-e49e10885fef",
            "isPostseason": false,
            "league": "San Francisco Bay League",
            "team1Color": "#53917e",
            "team2Color": "#ffb627"
        },
        {
            "team1Name": "Richmond Slicks",
            "team1Abbr": "RS",
            "team2Name": "Sutro Tower",
            "team2Abbr": "ST",
            "patternName": "stlouis",
            "season": 13,
            "day": 4,
            "id": "89e350d1-e4a6-4ad6-98fe-12c6c64351cb",
            "isPostseason": false,
            "league": "San Francisco Bay League",
            "team1Color": "#e7a0e8",
            "team2Color": "#ff1717"
        }
    ],
    [
        {
            "team1Name": "Santa Cruz Bananas",
            "team1Abbr": "SCB",
            "team2Name": "Carmel Yacht Club",
            "team2Abbr": "CYC",
            "patternName": "precipitation",
            "season": 13,
            "day": 5,
            "id": "1afe11a2-484a-498a-84b0-c070189a9cbc",
            "isPostseason": false,
            "league": "Monterey Bay League",
            "team1Color": "#fefe67",
            "team2Color": "#e7d7c1"
        },
        {
            "team1Name": "Boulder Creek Cardsharps",
            "team1Abbr": "BCC",
            "team2Name": "Aptos Investigators",
            "team2Abbr": "AI",
            "patternName": "fishsoup",
            "season": 13,
            "day": 5,
            "id": "891c8c40-e0e1-47c4-a227-bb4b865170ed",
            "isPostseason": false,
            "league": "Monterey Bay League",
            "team1Color": "#00cc44",
            "team2Color": "#3e92cc"
        },
        {
            "team1Name": "Freedom Fries",
            "team1Abbr": "FFR",
            "team2Name": "Monterey Meteorologists",
            "team2Abbr": "MM",
            "patternName": "kitchensink",
            "season": 13,
            "day": 5,
            "id": "f2cac11e-29c5-4ced-bbf8-bfa156731bdf",
            "isPostseason": false,
            "league": "Monterey Bay League",
            "team1Color": "#a0e7e5",
            "team2Color": "#ff66cc"
        },
        {
            "team1Name": "Sand City Sidewinders",
            "team1Abbr": "SCS",
            "team2Name": "Moss Landing Daredevils",
            "team2Abbr": "DD",
            "patternName": "rustytank",
            "season": 13,
            "day": 5,
            "id": "088616ed-573c-407d-86ed-57c0630a8645",
            "isPostseason": false,
            "league": "Monterey Bay League",
            "team1Color": "#bb0000",
            "team2Color": "#9963ab"
        },
        {
            "team1Name": "Pacific Grove Monarchists",
            "team1Abbr": "PGM",
            "team2Name": "Davenport Cliff Divers",
            "team2Abbr": "DCD",
            "patternName": "random",
            "season": 13,
            "day": 5,
            "id": "2446e0bb-1b2a-4b63-a1c9-1aca574ef36c",
            "isPostseason": false,
            "league": "Monterey Bay League",
            "team1Color": "#e86215",
            "team2Color": "#f2c57c"
        },
        {
            "team1Name": "Mountain View Miners",
            "team1Abbr": "MVM",
            "team2Name": "Sausalito Bouncy Castles",
            "team2Abbr": "SBC",
            "patternName": "chicago",
            "season": 13,
            "day": 5,
            "id": "24c622e8-eff8-4122-b0f3-f4095a0fa2e0",
            "isPostseason": false,
            "league": "San Francisco Bay League",
            "team1Color": "#f08700",
            "team2Color": "#0dab76"
        },
        {
            "team1Name": "San Jose Avionics",
            "team1Abbr": "SJA",
            "team2Name": "Vallejo Barnstormers",
            "team2Abbr": "VB",
            "patternName": "fishsoup",
            "season": 13,
            "day": 5,
            "id": "d60e6dcc-7ed3-4917-bc2c-fd57383ff78e",
            "isPostseason": false,
            "league": "San Francisco Bay League",
            "team1Color": "#53917e",
            "team2Color": "#697a21"
        },
        {
            "team1Name": "Oakland Bees",
            "team1Abbr": "OB",
            "team2Name": "Sutro Tower",
            "team2Abbr": "ST",
            "patternName": "denaturation",
            "season": 13,
            "day": 5,
            "id": "accdd338-5ca4-4a9e-a984-1ef895065dc6",
            "isPostseason": false,
            "league": "San Francisco Bay League",
            "team1Color": "#ffb627",
            "team2Color": "#ff1717"
        },
        {
            "team1Name": "Richmond Slicks",
            "team1Abbr": "RS",
            "team2Name": "Hayward Pipelines",
            "team2Abbr": "HP",
            "patternName": "precipitation",
            "season": 13,
            "day": 5,
            "id": "d1c44cd7-68b1-4fb2-8a1a-c53d039fa22d",
            "isPostseason": false,
            "league": "San Francisco Bay League",
            "team1Color": "#e7a0e8",
            "team2Color": "#b0b0b0"
        },
        {
            "team1Name": "San Gregorio Sand Crabs",
            "team1Abbr": "SGSC",
            "team2Name": "Berkeley Brutalists",
            "team2Abbr": "BBR",
            "patternName": "evaporation",
            "season": 13,
            "day": 5,
            "id": "9dc56f6f-528a-4d62-bd26-0fbdf6e0c263",
            "isPostseason": false,
            "league": "San Francisco Bay League",
            "team1Color": "#ef6f6c",
            "team2Color": "#d41199"
        }
    ],
    [
        {
            "team1Name": "Carmel Yacht Club",
            "team1Abbr": "CYC",
            "team2Name": "Boulder Creek Cardsharps",
            "team2Abbr": "BCC",
            "patternName": "flyingv2",
            "season": 13,
            "day": 6,
            "id": "e6c178c2-34ac-4b39-9ba3-6c70c3880597",
            "isPostseason": false,
            "league": "Monterey Bay League",
            "team1Color": "#e7d7c1",
            "team2Color": "#00cc44"
        },
        {
            "team1Name": "Santa Cruz Bananas",
            "team1Abbr": "SCB",
            "team2Name": "Davenport Cliff Divers",
            "team2Abbr": "DCD",
            "patternName": "flyingv2",
            "season": 13,
            "day": 6,
            "id": "3a3e7cc2-a724-4e6f-a796-7a5b5c689e48",
            "isPostseason": false,
            "league": "Monterey Bay League",
            "team1Color": "#fefe67",
            "team2Color": "#f2c57c"
        },
        {
            "team1Name": "Sand City Sidewinders",
            "team1Abbr": "SCS",
            "team2Name": "Freedom Fries",
            "team2Abbr": "FFR",
            "patternName": "ricepudding",
            "season": 13,
            "day": 6,
            "id": "649053a8-0ef7-4368-add4-11cb3fa41d79",
            "isPostseason": false,
            "league": "Monterey Bay League",
            "team1Color": "#bb0000",
            "team2Color": "#a0e7e5"
        },
        {
            "team1Name": "Monterey Meteorologists",
            "team1Abbr": "MM",
            "team2Name": "Aptos Investigators",
            "team2Abbr": "AI",
            "patternName": "flyingv1",
            "season": 13,
            "day": 6,
            "id": "7c65d8db-9fb9-40dd-a04d-1b737784dcb6",
            "isPostseason": false,
            "league": "Monterey Bay League",
            "team1Color": "#ff66cc",
            "team2Color": "#3e92cc"
        },
        {
            "team1Name": "Moss Landing Daredevils",
            "team1Abbr": "DD",
            "team2Name": "Pacific Grove Monarchists",
            "team2Abbr": "PGM",
            "patternName": "dessertplate",
            "season": 13,
            "day": 6,
            "id": "fbb39fbf-006d-41ab-b93a-65c5f3d475e5",
            "isPostseason": false,
            "league": "Monterey Bay League",
            "team1Color": "#9963ab",
            "team2Color": "#e86215"
        },
        {
            "team1Name": "Vallejo Barnstormers",
            "team1Abbr": "VB",
            "team2Name": "Hayward Pipelines",
            "team2Abbr": "HP",
            "patternName": "flyingv2",
            "season": 13,
            "day": 6,
            "id": "fce8394e-5d9a-4853-99b4-95dcbc76e424",
            "isPostseason": false,
            "league": "San Francisco Bay League",
            "team1Color": "#697a21",
            "team2Color": "#b0b0b0"
        },
        {
            "team1Name": "Sausalito Bouncy Castles",
            "team1Abbr": "SBC",
            "team2Name": "Sutro Tower",
            "team2Abbr": "ST",
            "patternName": "dinnerplate",
            "season": 13,
            "day": 6,
            "id": "973a8f4a-367e-4b32-9ad3-b62f7139f9a3",
            "isPostseason": false,
            "league": "San Francisco Bay League",
            "team1Color": "#0dab76",
            "team2Color": "#ff1717"
        },
        {
            "team1Name": "San Gregorio Sand Crabs",
            "team1Abbr": "SGSC",
            "team2Name": "Mountain View Miners",
            "team2Abbr": "MVM",
            "patternName": "flyingv2",
            "season": 13,
            "day": 6,
            "id": "8970258a-3499-4505-90c5-909d2ce2ca8d",
            "isPostseason": false,
            "league": "San Francisco Bay League",
            "team1Color": "#ef6f6c",
            "team2Color": "#f08700"
        },
        {
            "team1Name": "Berkeley Brutalists",
            "team1Abbr": "BBR",
            "team2Name": "Richmond Slicks",
            "team2Abbr": "RS",
            "patternName": "evaporation",
            "season": 13,
            "day": 6,
            "id": "c3c53b56-559c-4d9f-a4bc-f27de73c03d4",
            "isPostseason": false,
            "league": "San Francisco Bay League",
            "team1Color": "#d41199",
            "team2Color": "#e7a0e8"
        },
        {
            "team1Name": "Oakland Bees",
            "team1Abbr": "OB",
            "team2Name": "San Jose Avionics",
            "team2Abbr": "SJA",
            "patternName": "combs",
            "season": 13,
            "day": 6,
            "id": "fb061fd1-79bb-4f4f-8be6-92a82ed19f30",
            "isPostseason": false,
            "league": "San Francisco Bay League",
            "team1Color": "#ffb627",
            "team2Color": "#53917e"
        }
    ],
    [
        {
            "team1Name": "Aptos Investigators",
            "team1Abbr": "AI",
            "team2Name": "Boulder Creek Cardsharps",
            "team2Abbr": "BCC",
            "patternName": "precipitation",
            "season": 13,
            "day": 7,
            "id": "c915a8a7-4482-4151-8243-7c0eb9893304",
            "isPostseason": false,
            "league": "Monterey Bay League",
            "team1Color": "#3e92cc",
            "team2Color": "#00cc44"
        },
        {
            "team1Name": "Freedom Fries",
            "team1Abbr": "FFR",
            "team2Name": "Carmel Yacht Club",
            "team2Abbr": "CYC",
            "patternName": "ricepudding",
            "season": 13,
            "day": 7,
            "id": "f970b98f-1ebf-46af-a19c-7a518a305c45",
            "isPostseason": false,
            "league": "Monterey Bay League",
            "team1Color": "#a0e7e5",
            "team2Color": "#e7d7c1"
        },
        {
            "team1Name": "Davenport Cliff Divers",
            "team1Abbr": "DCD",
            "team2Name": "Pacific Grove Monarchists",
            "team2Abbr": "PGM",
            "patternName": "stlouis",
            "season": 13,
            "day": 7,
            "id": "aaa7df81-73e0-47a6-818a-cd7f1fdefaa8",
            "isPostseason": false,
            "league": "Monterey Bay League",
            "team1Color": "#f2c57c",
            "team2Color": "#e86215"
        },
        {
            "team1Name": "Monterey Meteorologists",
            "team1Abbr": "MM",
            "team2Name": "Santa Cruz Bananas",
            "team2Abbr": "SCB",
            "patternName": "kitchensink",
            "season": 13,
            "day": 7,
            "id": "45d07bad-badf-4007-8eb8-23d34f8bb74b",
            "isPostseason": false,
            "league": "Monterey Bay League",
            "team1Color": "#ff66cc",
            "team2Color": "#fefe67"
        },
        {
            "team1Name": "Moss Landing Daredevils",
            "team1Abbr": "DD",
            "team2Name": "Sand City Sidewinders",
            "team2Abbr": "SCS",
            "patternName": "chicago",
            "season": 13,
            "day": 7,
            "id": "d778d479-315e-4d91-b939-a3e41769d9fd",
            "isPostseason": false,
            "league": "Monterey Bay League",
            "team1Color": "#9963ab",
            "team2Color": "#bb0000"
        },
        {
            "team1Name": "San Jose Avionics",
            "team1Abbr": "SJA",
            "team2Name": "Berkeley Brutalists",
            "team2Abbr": "BBR",
            "patternName": "fishsoup",
            "season": 13,
            "day": 7,
            "id": "e0eac90f-8cca-44b3-9f0c-29c16b7375da",
            "isPostseason": false,
            "league": "San Francisco Bay League",
            "team1Color": "#53917e",
            "team2Color": "#d41199"
        },
        {
            "team1Name": "Richmond Slicks",
            "team1Abbr": "RS",
            "team2Name": "Vallejo Barnstormers",
            "team2Abbr": "VB",
            "patternName": "rustytank",
            "season": 13,
            "day": 7,
            "id": "3e55258c-d215-401f-acdf-84d3cade88cf",
            "isPostseason": false,
            "league": "San Francisco Bay League",
            "team1Color": "#e7a0e8",
            "team2Color": "#697a21"
        },
        {
            "team1Name": "Sausalito Bouncy Castles",
            "team1Abbr": "SBC",
            "team2Name": "San Gregorio Sand Crabs",
            "team2Abbr": "SGSC",
            "patternName": "gastank",
            "season": 13,
            "day": 7,
            "id": "d5ec23fc-7aa5-46c9-9b25-fedbf6cd990f",
            "isPostseason": false,
            "league": "San Francisco Bay League",
            "team1Color": "#0dab76",
            "team2Color": "#ef6f6c"
        },
        {
            "team1Name": "Mountain View Miners",
            "team1Abbr": "MVM",
            "team2Name": "Hayward Pipelines",
            "team2Abbr": "HP",
            "patternName": "dessertplate",
            "season": 13,
            "day": 7,
            "id": "5dd0c98c-1e03-42d5-9ac4-e8973a926561",
            "isPostseason": false,
            "league": "San Francisco Bay League",
            "team1Color": "#f08700",
            "team2Color": "#b0b0b0"
        },
        {
            "team1Name": "Oakland Bees",
            "team1Abbr": "OB",
            "team2Name": "Sutro Tower",
            "team2Abbr": "ST",
            "patternName": "dinnerplate",
            "season": 13,
            "day": 7,
            "id": "b6a87b47-f299-4ae8-911f-ee9df141afe3",
            "isPostseason": false,
            "league": "San Francisco Bay League",
            "team1Color": "#ffb627",
            "team2Color": "#ff1717"
        }
    ],
    [
        {
            "team1Name": "Boulder Creek Cardsharps",
            "team1Abbr": "BCC",
            "team2Name": "Monterey Meteorologists",
            "team2Abbr": "MM",
            "patternName": "precipitation",
            "season": 13,
            "day": 8,
            "id": "e323ba65-2a22-43d8-bd08-835c3302fd6c",
            "isPostseason": false,
            "league": "Monterey Bay League",
            "team1Color": "#00cc44",
            "team2Color": "#ff66cc"
        },
        {
            "team1Name": "Aptos Investigators",
            "team1Abbr": "AI",
            "team2Name": "Santa Cruz Bananas",
            "team2Abbr": "SCB",
            "patternName": "stlouis",
            "season": 13,
            "day": 8,
            "id": "26d4ba44-fa66-4dc5-b53c-4b05a7a459f2",
            "isPostseason": false,
            "league": "Monterey Bay League",
            "team1Color": "#3e92cc",
            "team2Color": "#fefe67"
        },
        {
            "team1Name": "Pacific Grove Monarchists",
            "team1Abbr": "PGM",
            "team2Name": "Moss Landing Daredevils",
            "team2Abbr": "DD",
            "patternName": "squarestar",
            "season": 13,
            "day": 8,
            "id": "60d0f29f-41cd-4874-afc1-ca7acf52e8ea",
            "isPostseason": false,
            "league": "Monterey Bay League",
            "team1Color": "#e86215",
            "team2Color": "#9963ab"
        },
        {
            "team1Name": "Davenport Cliff Divers",
            "team1Abbr": "DCD",
            "team2Name": "Freedom Fries",
            "team2Abbr": "FFR",
            "patternName": "dinnerplate",
            "season": 13,
            "day": 8,
            "id": "9dc5f970-89da-406b-9ddc-6b8d7082a964",
            "isPostseason": false,
            "league": "Monterey Bay League",
            "team1Color": "#f2c57c",
            "team2Color": "#a0e7e5"
        },
        {
            "team1Name": "Sand City Sidewinders",
            "team1Abbr": "SCS",
            "team2Name": "Carmel Yacht Club",
            "team2Abbr": "CYC",
            "patternName": "flyingv1",
            "season": 13,
            "day": 8,
            "id": "956b0d4f-827f-4b28-8c3e-d7cf7645ae6b",
            "isPostseason": false,
            "league": "Monterey Bay League",
            "team1Color": "#bb0000",
            "team2Color": "#e7d7c1"
        },
        {
            "team1Name": "San Jose Avionics",
            "team1Abbr": "SJA",
            "team2Name": "Mountain View Miners",
            "team2Abbr": "MVM",
            "patternName": "denaturation",
            "season": 13,
            "day": 8,
            "id": "c23dbf60-5a31-4c67-b1b0-799e11566265",
            "isPostseason": false,
            "league": "San Francisco Bay League",
            "team1Color": "#53917e",
            "team2Color": "#f08700"
        },
        {
            "team1Name": "Berkeley Brutalists",
            "team1Abbr": "BBR",
            "team2Name": "Vallejo Barnstormers",
            "team2Abbr": "VB",
            "patternName": "chicago",
            "season": 13,
            "day": 8,
            "id": "2a0ca423-3eb1-4f3b-aae0-f81ed1b9bafb",
            "isPostseason": false,
            "league": "San Francisco Bay League",
            "team1Color": "#d41199",
            "team2Color": "#697a21"
        },
        {
            "team1Name": "Sutro Tower",
            "team1Abbr": "ST",
            "team2Name": "Sausalito Bouncy Castles",
            "team2Abbr": "SBC",
            "patternName": "rustytank",
            "season": 13,
            "day": 8,
            "id": "ff125e3e-56ab-4918-be07-d679eb210efe",
            "isPostseason": false,
            "league": "San Francisco Bay League",
            "team1Color": "#ff1717",
            "team2Color": "#0dab76"
        },
        {
            "team1Name": "San Gregorio Sand Crabs",
            "team1Abbr": "SGSC",
            "team2Name": "Hayward Pipelines",
            "team2Abbr": "HP",
            "patternName": "evaporation",
            "season": 13,
            "day": 8,
            "id": "fb057949-ae93-4f48-bf6c-04850d765872",
            "isPostseason": false,
            "league": "San Francisco Bay League",
            "team1Color": "#ef6f6c",
            "team2Color": "#b0b0b0"
        },
        {
            "team1Name": "Richmond Slicks",
            "team1Abbr": "RS",
            "team2Name": "Oakland Bees",
            "team2Abbr": "OB",
            "patternName": "flyingv2",
            "season": 13,
            "day": 8,
            "id": "ca410111-8004-44de-ba8b-7f52f35500f2",
            "isPostseason": false,
            "league": "San Francisco Bay League",
            "team1Color": "#e7a0e8",
            "team2Color": "#ffb627"
        }
    ],
    [
        {
            "team1Name": "Aptos Investigators",
            "team1Abbr": "AI",
            "team2Name": "Carmel Yacht Club",
            "team2Abbr": "CYC",
            "patternName": "ricepudding",
            "season": 13,
            "day": 9,
            "id": "57002753-79b4-4e3c-8320-ca0e92125a05",
            "isPostseason": false,
            "league": "Monterey Bay League",
            "team1Color": "#3e92cc",
            "team2Color": "#e7d7c1"
        },
        {
            "team1Name": "Boulder Creek Cardsharps",
            "team1Abbr": "BCC",
            "team2Name": "Santa Cruz Bananas",
            "team2Abbr": "SCB",
            "patternName": "denaturation",
            "season": 13,
            "day": 9,
            "id": "9abe8af5-9f38-4564-8c1d-9676d84cf3cd",
            "isPostseason": false,
            "league": "Monterey Bay League",
            "team1Color": "#00cc44",
            "team2Color": "#fefe67"
        },
        {
            "team1Name": "Freedom Fries",
            "team1Abbr": "FFR",
            "team2Name": "Davenport Cliff Divers",
            "team2Abbr": "DCD",
            "patternName": "newyork",
            "season": 13,
            "day": 9,
            "id": "b35b1731-71df-485c-ac3c-6adf9bb1ea93",
            "isPostseason": false,
            "league": "Monterey Bay League",
            "team1Color": "#a0e7e5",
            "team2Color": "#f2c57c"
        },
        {
            "team1Name": "Sand City Sidewinders",
            "team1Abbr": "SCS",
            "team2Name": "Monterey Meteorologists",
            "team2Abbr": "MM",
            "patternName": "stlouis",
            "season": 13,
            "day": 9,
            "id": "fa5a8b3e-1bb2-4e00-bb39-149c28c44299",
            "isPostseason": false,
            "league": "Monterey Bay League",
            "team1Color": "#bb0000",
            "team2Color": "#ff66cc"
        },
        {
            "team1Name": "Moss Landing Daredevils",
            "team1Abbr": "DD",
            "team2Name": "Pacific Grove Monarchists",
            "team2Abbr": "PGM",
            "patternName": "dessertplate",
            "season": 13,
            "day": 9,
            "id": "4a33ecdf-0880-495c-a985-ee823bf384d6",
            "isPostseason": false,
            "league": "Monterey Bay League",
            "team1Color": "#9963ab",
            "team2Color": "#e86215"
        },
        {
            "team1Name": "Sutro Tower",
            "team1Abbr": "ST",
            "team2Name": "Mountain View Miners",
            "team2Abbr": "MVM",
            "patternName": "stlouis",
            "season": 13,
            "day": 9,
            "id": "6df88ecd-1a8b-4082-9c69-41dfd6fd776f",
            "isPostseason": false,
            "league": "San Francisco Bay League",
            "team1Color": "#ff1717",
            "team2Color": "#f08700"
        },
        {
            "team1Name": "Oakland Bees",
            "team1Abbr": "OB",
            "team2Name": "Vallejo Barnstormers",
            "team2Abbr": "VB",
            "patternName": "random",
            "season": 13,
            "day": 9,
            "id": "bdf99cc8-50eb-4427-a3cb-896bedc4d592",
            "isPostseason": false,
            "league": "San Francisco Bay League",
            "team1Color": "#ffb627",
            "team2Color": "#697a21"
        },
        {
            "team1Name": "San Jose Avionics",
            "team1Abbr": "SJA",
            "team2Name": "San Gregorio Sand Crabs",
            "team2Abbr": "SGSC",
            "patternName": "flyingv1",
            "season": 13,
            "day": 9,
            "id": "8d35ca6b-749d-495e-8576-177008094b71",
            "isPostseason": false,
            "league": "San Francisco Bay League",
            "team1Color": "#53917e",
            "team2Color": "#ef6f6c"
        },
        {
            "team1Name": "Hayward Pipelines",
            "team1Abbr": "HP",
            "team2Name": "Sausalito Bouncy Castles",
            "team2Abbr": "SBC",
            "patternName": "evaporation",
            "season": 13,
            "day": 9,
            "id": "a4bf20d3-ee80-408e-a9b2-b7e5cba30266",
            "isPostseason": false,
            "league": "San Francisco Bay League",
            "team1Color": "#b0b0b0",
            "team2Color": "#0dab76"
        },
        {
            "team1Name": "Richmond Slicks",
            "team1Abbr": "RS",
            "team2Name": "Berkeley Brutalists",
            "team2Abbr": "BBR",
            "patternName": "stlouis",
            "season": 13,
            "day": 9,
            "id": "5157c3e1-ca38-4786-8131-1ad354915711",
            "isPostseason": false,
            "league": "San Francisco Bay League",
            "team1Color": "#e7a0e8",
            "team2Color": "#d41199"
        }
    ],
    [
        {
            "team1Name": "Carmel Yacht Club",
            "team1Abbr": "CYC",
            "team2Name": "Pacific Grove Monarchists",
            "team2Abbr": "PGM",
            "patternName": "ricepudding",
            "season": 13,
            "day": 10,
            "id": "6443e65f-6bc3-4704-b20f-f8b34d51fe21",
            "isPostseason": false,
            "league": "Monterey Bay League",
            "team1Color": "#e7d7c1",
            "team2Color": "#e86215"
        },
        {
            "team1Name": "Freedom Fries",
            "team1Abbr": "FFR",
            "team2Name": "Davenport Cliff Divers",
            "team2Abbr": "DCD",
            "patternName": "rustytank",
            "season": 13,
            "day": 10,
            "id": "568cfbfb-9cad-491b-a017-26124a7b4537",
            "isPostseason": false,
            "league": "Monterey Bay League",
            "team1Color": "#a0e7e5",
            "team2Color": "#f2c57c"
        },
        {
            "team1Name": "Aptos Investigators",
            "team1Abbr": "AI",
            "team2Name": "Monterey Meteorologists",
            "team2Abbr": "MM",
            "patternName": "chicago",
            "season": 13,
            "day": 10,
            "id": "1a4eb83a-69a0-4f9a-b71b-1e2427ce23ec",
            "isPostseason": false,
            "league": "Monterey Bay League",
            "team1Color": "#3e92cc",
            "team2Color": "#ff66cc"
        },
        {
            "team1Name": "Sand City Sidewinders",
            "team1Abbr": "SCS",
            "team2Name": "Boulder Creek Cardsharps",
            "team2Abbr": "BCC",
            "patternName": "flyingv2",
            "season": 13,
            "day": 10,
            "id": "8cf4bdfa-9da5-48b1-83fd-bf38af168917",
            "isPostseason": false,
            "league": "Monterey Bay League",
            "team1Color": "#bb0000",
            "team2Color": "#00cc44"
        },
        {
            "team1Name": "Moss Landing Daredevils",
            "team1Abbr": "DD",
            "team2Name": "Santa Cruz Bananas",
            "team2Abbr": "SCB",
            "patternName": "ricepudding",
            "season": 13,
            "day": 10,
            "id": "1350b826-119f-4bf3-9d00-a1d1ea0fa6cb",
            "isPostseason": false,
            "league": "Monterey Bay League",
            "team1Color": "#9963ab",
            "team2Color": "#fefe67"
        },
        {
            "team1Name": "Vallejo Barnstormers",
            "team1Abbr": "VB",
            "team2Name": "Mountain View Miners",
            "team2Abbr": "MVM",
            "patternName": "evaporation",
            "season": 13,
            "day": 10,
            "id": "32e25134-86b7-4a09-b76f-44e47077978d",
            "isPostseason": false,
            "league": "San Francisco Bay League",
            "team1Color": "#697a21",
            "team2Color": "#f08700"
        },
        {
            "team1Name": "Sutro Tower",
            "team1Abbr": "ST",
            "team2Name": "Hayward Pipelines",
            "team2Abbr": "HP",
            "patternName": "random",
            "season": 13,
            "day": 10,
            "id": "19cee7ef-1192-4cb4-9dc0-6be7d15e4d99",
            "isPostseason": false,
            "league": "San Francisco Bay League",
            "team1Color": "#ff1717",
            "team2Color": "#b0b0b0"
        },
        {
            "team1Name": "Oakland Bees",
            "team1Abbr": "OB",
            "team2Name": "San Jose Avionics",
            "team2Abbr": "SJA",
            "patternName": "chicago",
            "season": 13,
            "day": 10,
            "id": "101d5db2-48c0-40ce-ac9a-d3d599f9d9cd",
            "isPostseason": false,
            "league": "San Francisco Bay League",
            "team1Color": "#ffb627",
            "team2Color": "#53917e"
        },
        {
            "team1Name": "Sausalito Bouncy Castles",
            "team1Abbr": "SBC",
            "team2Name": "Berkeley Brutalists",
            "team2Abbr": "BBR",
            "patternName": "stlouis",
            "season": 13,
            "day": 10,
            "id": "df70df23-e885-4ed9-ac96-f723ae99e7b9",
            "isPostseason": false,
            "league": "San Francisco Bay League",
            "team1Color": "#0dab76",
            "team2Color": "#d41199"
        },
        {
            "team1Name": "San Gregorio Sand Crabs",
            "team1Abbr": "SGSC",
            "team2Name": "Richmond Slicks",
            "team2Abbr": "RS",
            "patternName": "squarestar",
            "season": 13,
            "day": 10,
            "id": "66cd536b-c51d-4046-b238-e5e0ce4842ae",
            "isPostseason": false,
            "league": "San Francisco Bay League",
            "team1Color": "#ef6f6c",
            "team2Color": "#e7a0e8"
        }
    ]
]